{"id": "5b157d4c-eaf7-49bd-a2a1-d4ed7c7ac806", "url": "https://www.citigroup.com/global/news/press-release/2023/citi-libor-transition-update-09-2023", "title": "Citi LIBOR Transition Update", "summary": "<p>Update Regarding Fallback Provisions for Outstanding US Law-Governed Citi-Issued USD LIBOR CMS Instruments</p>", "tag-1": "Citi LIBOR Transition Update", "tag-2": "Update Regarding Fallback Provisions for Outstanding US Law-Governed Citi-Issued USD LIBOR CMS Instruments", "tag-3": "NEW YORK \u2013 On June 30, 2023 (the \u201cCessation Date\u201d), ICE Benchmark Administration (\u201cIBA\u201d) ceased publication of all ICE Swap Rate settings based on USD LIBOR. \u00a0This cessation followed the announcement by the UK Financial Conduct Authority on March 5, 2021, that all USD LIBOR settings would either cease or no longer be representative after the Cessation Date. The USD LIBOR ICE Swap Rate is also referred to as a constant maturity swap (or \u201cCMS\u201d) rate, and in this press release is referred to as the \u201cUSD LIBOR CMS Rate\u201d.", "tag-4": "Citigroup Inc. and certain of its consolidated subsidiaries have issued debt securities, certificates of deposit, preferred stock, asset-backed securities and trust preferred securities that:", "tag-5": "Citi is issuing this press release to provide notice that, pursuant to the fallback provisions in each Legacy CMS Instrument, each determination of the USD LIBOR CMS Rate to be made under the terms of the Legacy CMS Instruments after the Cessation Date will be made by reference to the USD SOFR Spread-Adjusted ICE Swap Rate\u00ae for the corresponding tenor as published by IBA (or any successor) for so long as such rate is published.", "tag-6": "This press release updates information provided in a previous press release relating to the Legacy CMS Instruments dated May 11, 2023. \u00a0The Legacy CMS Instruments in scope of this press release are listed on the annex to this press release.", "tag-7": "The applicable issuer has filed a registration statement (including a prospectus) with the Securities and Exchange Commission (\u201cSEC\u201d) for certain of the securities to which this communication relates. Before investing, any investor should read the prospectus in that registration statement and the other documents the issuer has filed with the SEC for more complete information about the issuer and such securities. \u00a0Any investor may obtain these documents without cost by visiting EDGAR on the SEC website at www.sec.gov. Alternatively, any investor can request these documents from Citigroup Global Markets Inc., c/o Broadridge Financial Solutions, 1155 Long Island Avenue, Edgewood, NY 11717, telephone: (800) 831-9146 or email: prospectus@citi.com.", "tag-8": "Annex", "tag-9": "Issuer: Citigroup Inc.", "tag-10": "CUSIP", "tag-11": "1730T0TZ2", "tag-12": "17298CBZ0", "tag-13": "17298CLW6", "tag-14": "1730T0E21", "tag-15": "17298CDA3", "tag-16": "1730T0HV4", "tag-17": "1730T0RN1", "tag-18": "1730T3AU7", "tag-19": "1730T0KZ1", "tag-20": "1730T0TK5", "tag-21": "1730T3AV5", "tag-22": "1730T0HN2", "tag-23": "1730T0TQ2", "tag-24": "1730T3AW3", "tag-25": "1730T0JN0", "tag-26": "1730T0TT6", "tag-27": "17298C3F3", "tag-28": "1730T0LH0", "tag-29": "1730T0UB3", "tag-30": "17298C3Y2", "tag-31": "1730T0KV0", "tag-32": "1730T0UG2", "tag-33": "17298C6K9", "tag-34": "1730T0SM2", "tag-35": "1730T0UK3", "tag-36": "1730T0X46", "tag-37": "1730T0R50", "tag-38": "1730T0VD8", "tag-39": "1730T02D0", "tag-40": "17298CAT5", "tag-41": "1730T0A58", "tag-42": "1730T02B4", "tag-43": "1730T06G9", "tag-44": "1730T0A82", "tag-45": "1730T02V0", "tag-46": "1730T07D5", "tag-47": "1730T0A90", "tag-48": "1730T03J6", "tag-49": "17298CAD0", "tag-50": "1730T0C23", "tag-51": "1730T03W7", "tag-52": "17298CAF5", "tag-53": "1730T0C56", "tag-54": "1730T04U0", "tag-55": "17298CBB3", "tag-56": "1730T0T58", "tag-57": "17298CAR9", "tag-58": "17298CGL6", "tag-59": "1730T02P3", "tag-60": "17298CCL0", "tag-61": "17298CGS1", "tag-62": "1730T0E96", "tag-63": "1730T3AX1", "tag-64": "17298CGZ5", "tag-65": "1730T0G78", "tag-66": "1730T3AY9", "tag-67": "1730T04K2", "tag-68": "1730T0K32", "tag-69": "1730T3AZ6", "tag-70": "1730T04Y2", "tag-71": "1730T0L31", "tag-72": "17298CFQ6", "tag-73": "1730T05M7", "tag-74": "1730T0L64", "tag-75": "17298CFV5", "tag-76": "17298CG77", "tag-77": "1730T0N62", "tag-78": "17298CG36", "tag-79": "17298CGD4", "tag-80": "1730T0P86", "tag-81": "17298CG69", "tag-82": "17298CGE2", "tag-83": "1730T0U49", "tag-84": "1730T0R76", "tag-85": "17298CGK8", "tag-86": "1730T0W21", "tag-87": "1730T07K9", "tag-88": "Issuer: Citigroup Global Markets Holdings Inc.", "tag-89": "CUSIP", "tag-90": "17324CGG5", "tag-91": "17327TC38", "tag-92": "17324CZA7", "tag-93": "17328WJS8", "tag-94": "17328YYU2", "tag-95": "17329U3F6", "tag-96": "17324CHL3", "tag-97": "17327TG34", "tag-98": "17326YH41", "tag-99": "17328WKS6", "tag-100": "17328YU69", "tag-101": "17329UHX2", "tag-102": "17324CHH2", "tag-103": "17327TK54", "tag-104": "17324CR65", "tag-105": "17328WRC4", "tag-106": "17328YU85", "tag-107": "17329UEA5", "tag-108": "17324CP34", "tag-109": "17327TH90", "tag-110": "17326YND4", "tag-111": "17328WT24", "tag-112": "17328YY99", "tag-113": "17329UCD1", "tag-114": "17326YKV7", "tag-115": "17327T3U8", "tag-116": "17326YVA1", "tag-117": "17328WUU0", "tag-118": "17328YS70", "tag-119": "17329ULU3", "tag-120": "17326YQT6", "tag-121": "17328V2A7", "tag-122": "17326YXP6", "tag-123": "17328WXG8", "tag-124": "17328YRS5", "tag-125": "17329UAG6", "tag-126": "17324CRG3", "tag-127": "17328VDM9", "tag-128": "17326YCC8", "tag-129": "17328WTH1", "tag-130": "17328YXE9", "tag-131": "17329UKZ3", "tag-132": "17324CSG2", "tag-133": "17328V5F3", "tag-134": "17326YP91", "tag-135": "17328WTN8", "tag-136": "17328YRF3", "tag-137": "17329UD32", "tag-138": "17324CUT1", "tag-139": "17328VG53", "tag-140": "17326YYA8", "tag-141": "17328WQ68", "tag-142": "17329F6V1", "tag-143": "17329UF30", "tag-144": "17324CVW3", "tag-145": "17328VVN7", "tag-146": "17326YVR4", "tag-147": "17328WVX3", "tag-148": "17329FC93", "tag-149": "17329UYM7", "tag-150": "17324CVT0", "tag-151": "17328VRF9", "tag-152": "17326YL95", "tag-153": "17328WRM2", "tag-154": "17329F2E3", "tag-155": "17329UXB2", "tag-156": "17324CXL5", "tag-157": "17328VMM9", "tag-158": "17327TRA6", "tag-159": "17328WNC8", "tag-160": "17329FC36", "tag-161": "17329UQ87", "tag-162": "17328YSU9", "tag-163": "17328VJB7", "tag-164": "17326YCA2", "tag-165": "17328WXB9", "tag-166": "17329F6J8", "tag-167": "17329USZ5", "tag-168": "17329FJ62", "tag-169": "17328VQ52", "tag-170": "17327TC95", "tag-171": "17328WXH6", "tag-172": "17329F5M2", "tag-173": "17329UR94", "tag-174": "17329FTP9", "tag-175": "17328VNM8", "tag-176": "17327TJ23", "tag-177": "17328WZF8", "tag-178": "17329F7B4", "tag-179": "17329QKY5", "tag-180": "17290JAA9", "tag-181": "17328VVD9", "tag-182": "17327TY83", "tag-183": "17328Y3L6", "tag-184": "17329F4X9", "tag-185": "17329QVX5", "tag-186": "17324CHQ2", "tag-187": "17328W5M6", "tag-188": "17327TX50", "tag-189": "17328Y3Q5", "tag-190": "17329FFX7", "tag-191": "17329QW71", "tag-192": "17324CED4", "tag-193": "17328W2U1", "tag-194": "17327TR99", "tag-195": "17328Y2M5", "tag-196": "17329F2X1", "tag-197": "17329QPS3", "tag-198": "17324CKB1", "tag-199": "17328W4Y1", "tag-200": "17328WHK7", "tag-201": "17328Y2R4", "tag-202": "17329FFK5", "tag-203": "17329QQS2", "tag-204": "17324CLR5", "tag-205": "17328WAV0", "tag-206": "17328WJA7", "tag-207": "17328YH72", "tag-208": "17329FKB9", "tag-209": "17329QXR6", "tag-210": "17324CLA2", "tag-211": "17328W5K0", "tag-212": "17328WEM6", "tag-213": "17328YDR2", "tag-214": "17329FDA9", "tag-215": "17329U4U2", "tag-216": "17324CMJ2", "tag-217": "17328W3Y2", "tag-218": "17328WBS6", "tag-219": "17328YC44", "tag-220": "17329FE91", "tag-221": "17329UD40", "tag-222": "17324CGJ9", "tag-223": "17328WAR9", "tag-224": "17328WLX4", "tag-225": "17328WAF5", "tag-226": "17329FRU0", "tag-227": "17329UGK1", "tag-228": "17324CLU8", "tag-229": "17328W7K8", "tag-230": "17328WLT3", "tag-231": "17329FL93", "tag-232": "17329FPJ7", "tag-233": "17329U4M0", "tag-234": "17324CFE1", "tag-235": "17328WM96", "tag-236": "17328W7C6", "tag-237": "17329FVK7", "tag-238": "17329FDT8", "tag-239": "17329UUK5", "tag-240": "17324CXG6", "tag-241": "17328WGN2", "tag-242": "17328WG77", "tag-243": "17329FEG5", "tag-244": "17329FDV3", "tag-245": "17329UR86", "tag-246": "17324CYQ3", "tag-247": "17328WJ82", "tag-248": "17328WJZ2", "tag-249": "17329FY81", "tag-250": "17329FL85", "tag-251": "17324CJ64", "tag-252": "17328YY73", "tag-253": "17328YNH3", "tag-254": "17328YFV1", "tag-255": "17329FS96", "tag-256": "17329FMP6", "tag-257": "17329U6P1", "tag-258": "17328YQV9", "tag-259": "17328YXT6", "tag-260": "17328YCS1", "tag-261": "17328YT38", "tag-262": "17329FDG6", "tag-263": "17329U6E6", "tag-264": "17328YSW5", "tag-265": "17328YJT2", "tag-266": "17328YJW5", "tag-267": "17328YDL5", "tag-268": "17329FKT0", "tag-269": "17329U5E7", "tag-270": "17328YRR7", "tag-271": "17328YPN8", "tag-272": "17328YF58", "tag-273": "17328YBD5", "tag-274": "17329FXP4", "tag-275": "17329U7K1", "tag-276": "17328YZV9", "tag-277": "17328YK45", "tag-278": "17328YGL2", "tag-279": "17328YBK9", "tag-280": "17329FXS8", "tag-281": "17329UFJ5", "tag-282": "17329FCB8", "tag-283": "17328YLG7", "tag-284": "17328YHY3", "tag-285": "17328Y6U3", "tag-286": "17329FSB1", "tag-287": "17329ULR0", "tag-288": "17329FWM2", "tag-289": "17329QBM1", "tag-290": "17329QK90", "tag-291": "17329QP95", "tag-292": "17329U3P4", "tag-293": "17329QSM3", "tag-294": "17329FUC6", "tag-295": "17329QET3", "tag-296": "17329Q6S4", "tag-297": "17329QNX4", "tag-298": "17329U2C4", "tag-299": "17329QTS9", "tag-300": "17329FXV1", "tag-301": "17329QG79", "tag-302": "17329QAG5", "tag-303": "17329QUK4", "tag-304": "17329U3D1", "tag-305": "17329QPC8", "tag-306": "17329FUH5", "tag-307": "17329QAZ3", "tag-308": "17329QHD5", "tag-309": "17329QSV3", "tag-310": "17329U4V0", "tag-311": "17329U2J9", "tag-312": "17329FZ23", "tag-313": "17329QAZ3", "tag-314": "17329QD49", "tag-315": "17329QXS4", "tag-316": "17329UDP3", "tag-317": "17329QYS3", "tag-318": "17329FYS7", "tag-319": "17329QBM1", "tag-320": "17329QB74", "tag-321": "17329QUC2", "tag-322": "17329UHB0", "tag-323": "17329Q5C0", "tag-324": "17329FUM4", "tag-325": "17329QET3", "tag-326": "17329QH94", "tag-327": "17329QE30", "tag-328": "17329QD98", "tag-329": "17329Q2F6", "tag-330": "17329FVE1", "tag-331": "17329QG79", "tag-332": "17329QGM6", "tag-333": "17329QB41", "tag-334": "17329Q6P0", "tag-335": "17329FVW1", "tag-336": "17329QL24", "tag-337": "Issuer: Citibank, N.A. (CBNA)", "tag-338": "CUSIP", "tag-339": "172986GH8", "tag-340": "172986HR5", "tag-341": "172986HF1", "tag-342": "172986HA2", "tag-343": "172986HB0", "tag-344": "172986GV7", "tag-345": "172986GQ8", "tag-346": "172986HV6", "tag-347": "172986GY1", "tag-348": "172986HZ7", "tag-349": "172986HT1", "tag-350": "172986KD2", "tag-351": "172986GZ8", "tag-352": "172986JB8", "tag-353": "172986HD6", "tag-354": "172986JL6", "tag-355": "172986HN4", "tag-356": "172986CJ8", "tag-357": "172986HS3", "tag-358": "172986GW5", "tag-359": "172986HK0", "tag-360": "172986CK5", "tag-361": "About Citi", "tag-362": "Citi is a preeminent banking partner for institutions with cross-border needs, a global leader in wealth management and a valued personal bank in its home market of the United States. Citi does business in nearly 160 countries and jurisdictions, providing corporations, governments, investors, institutions and individuals with a broad range of financial products and services.", "tag-363": "Additional information may be found at\u00a0www.citigroup.com\u00a0| Twitter:\u00a0@Citi\u00a0| LinkedIn:\u00a0www.linkedin.com/company/citi\u00a0| YouTube:\u00a0www.youtube.com/citi\u00a0| Facebook:\u00a0www.facebook.com/citi", "tag-364": "Media Contact", "tag-365": "Danielle Romero Apsilos: (212) 816-2264, danielle.romeroapsilos@citi.com", "tag-366": "Fixed Income Investor Contact", "tag-367": "Peter Demoise: (212) 559-2718, peter.demoise@citi.com", "tag-368": "Alternatively, please contact the Issuer at iborq@citi.com if you have any questions about anything contained in this press release."}